README.md
setup.py
BotyMcBotface.egg-info/PKG-INFO
BotyMcBotface.egg-info/SOURCES.txt
BotyMcBotface.egg-info/dependency_links.txt
BotyMcBotface.egg-info/top_level.txt
botymcbotface/__init__.py
botymcbotface/async_irc.py
botymcbotface/irc.py