Metadata-Version: 1.2
Name: BotyMcBotface
Version: 1.1.0
Summary: Simple framework for making IRC bots.
Home-page: https://github.com/enfors/BotyMcBotface
Author: Christer Enfors
Author-email: christer.enfors@gmail.com
License: LGPL
Platform: UNKNOWN
Requires-Python: >=3
